jupyter_rsession_proxy/__init__.py
jupyter_rsession_proxy/icons/rstudio.svg
jupyter_rsession_proxy-2.4.0.dist-info/licenses/LICENSE
jupyter_rsession_proxy-2.4.0.dist-info/METADATA
jupyter_rsession_proxy-2.4.0.dist-info/WHEEL
jupyter_rsession_proxy-2.4.0.dist-info/entry_points.txt
jupyter_rsession_proxy-2.4.0.dist-info/top_level.txt
jupyter_rsession_proxy-2.4.0.dist-info/RECORD
