Metadata-Version: 2.4
Name: jupyter-rsession-proxy
Version: 2.4.0
Summary: Jupyter extension to proxy RStudio
Home-page: https://github.com/jupyterhub/jupyter-rsession-proxy
Author: Ryan Lovett & Yuvi Panda
Keywords: Jupyter
Classifier: Framework :: Jupyter
License-File: LICENSE
Requires-Dist: jupyter-server-proxy>4.1.0
Dynamic: author
Dynamic: classifier
Dynamic: home-page
Dynamic: keywords
Dynamic: license-file
Dynamic: requires-dist
Dynamic: summary
